aijson_db/__init__.py
aijson_db/actions/__init__.py
aijson_db/actions/execute_db_statement.py
aijson_db/actions/get_db_schema.py
aijson_db/tests/__init__.py
aijson_db/tests/conftest.py
aijson_db/tests/test_execute_db_statement.py
aijson_db/tests/test_get_db_schema.py
aijson_db-0.1.1.dist-info/LICENSE
aijson_db-0.1.1.dist-info/METADATA
aijson_db-0.1.1.dist-info/WHEEL
aijson_db-0.1.1.dist-info/entry_points.txt
aijson_db-0.1.1.dist-info/RECORD
